llama_index/llms/alephalpha/__init__.py
llama_index/llms/alephalpha/base.py
llama_index/llms/alephalpha/utils.py
llama_index_llms_alephalpha-0.4.1.dist-info/METADATA
llama_index_llms_alephalpha-0.4.1.dist-info/WHEEL
llama_index_llms_alephalpha-0.4.1.dist-info/licenses/LICENSE
llama_index_llms_alephalpha-0.4.1.dist-info/RECORD
