Metadata-Version: 2.4
Name: llama-index-llms-alephalpha
Version: 0.4.1
Summary: llama-index llms Aleph Alpha integration
Author-email: Ulan Yisaev <Ulan.Yisaev@nortal.com>
License-Expression: MIT
License-File: LICENSE
Requires-Python: <4.0,>=3.9
Requires-Dist: aleph-alpha-client<8,>=7.0.1
Requires-Dist: llama-index-core<0.15,>=0.13.0
